{"stat.useItem.minecraft.chest":2,"stat.mineBlock.minecraft.furnace":2,"stat.craftItem.minecraft.wooden_pickaxe":1,"stat.mineBlock.minecraft.sand":33,"stat.useItem.minecraft.cobblestone":23,"achievement.exploreAllBiomes":{"value":0,"progress":["Taiga M","Taiga","Extreme Hills","River"]},"stat.craftItem.minecraft.cooked_chicken":5,"stat.mineBlock.minecraft.glass":1,"stat.breakItem.minecraft.wooden_axe":1,"stat.useItem.minecraft.spruce_door":1,"stat.craftItem.minecraft.chest":2,"achievement.openInventory":65,"stat.craftItem.minecraft.furnace":1,"stat.craftItem.minecraft.spruce_door":3,"stat.craftItem.minecraft.torch":28,"stat.damageDealt":1215,"stat.mineBlock.minecraft.log":87,"stat.breakItem.minecraft.stone_shovel":1,"stat.killEntity.Cow":1,"stat.useItem.minecraft.planks":378,"stat.craftItem.minecraft.wooden_shovel":1,"stat.fallOneCm":5741,"stat.flyOneCm":11293,"achievement.buildWorkBench":1,"achievement.buildPickaxe":1,"stat.useItem.minecraft.furnace":3,"stat.breakItem.minecraft.stone_pickaxe":2,"stat.mineBlock.minecraft.spruce_fence":4,"stat.useItem.minecraft.cooked_chicken":6,"stat.damageTaken":1220,"stat.useItem.minecraft.torch":6,"stat.useItem.minecraft.stone_pickaxe":265,"stat.useItem.minecraft.ladder":2,"stat.breakItem.minecraft.wooden_pickaxe":1,"stat.craftItem.minecraft.stone_axe":2,"stat.mineBlock.minecraft.clay":1,"stat.useItem.minecraft.stone_sword":6,"stat.climbOneCm":14616,"stat.killEntity.Chicken":5,"stat.drop":15,"stat.craftItem.minecraft.stone_pickaxe":3,"stat.leaveGame":8,"achievement.mineWood":75,"stat.breakItem.minecraft.wooden_shovel":1,"stat.useItem.minecraft.glass":1,"stat.mineBlock.minecraft.red_flower":5,"achievement.buildBetterPickaxe":1,"stat.mineBlock.minecraft.crafting_table":6,"stat.killEntity.Spider":2,"stat.timeSinceDeath":142,"stat.craftItem.minecraft.glass":30,"stat.craftItem.minecraft.stone_shovel":2,"stat.mineBlock.minecraft.planks":82,"stat.useItem.minecraft.crafting_table":7,"stat.mineBlock.minecraft.leaves":27,"stat.craftItem.minecraft.stick":36,"stat.playOneMinute":145962,"stat.craftItem.minecraft.wooden_axe":1,"stat.entityKilledBy.Skeleton":1,"stat.useItem.minecraft.stone_shovel":208,"stat.killEntity.Skeleton":2,"stat.walkOneCm":474058,"stat.playerKills":1,"stat.mineBlock.minecraft.coal_ore":29,"stat.jump":340,"stat.craftItem.minecraft.stone":43,"stat.entityKilledBy.Zombie":2,"stat.mineBlock.minecraft.tallgrass":10,"stat.craftItem.minecraft.stone_sword":1,"stat.mineBlock.minecraft.ladder":1,"stat.deaths":3,"stat.useItem.minecraft.stone_axe":180,"stat.craftItem.minecraft.crafting_table":2,"stat.mobKills":10,"stat.mineBlock.minecraft.stone":228,"stat.craftItem.minecraft.planks":328,"stat.craftItem.minecraft.trapdoor":2,"stat.mineBlock.minecraft.dirt":401,"stat.useItem.minecraft.wooden_axe":60,"stat.useItem.minecraft.wooden_pickaxe":57,"stat.useItem.minecraft.wooden_shovel":66,"stat.useItem.minecraft.trapdoor":1,"stat.breakItem.minecraft.stone_axe":1,"stat.sprintOneCm":3806,"stat.useItem.minecraft.dirt":10}